src/diff_img.py
src/img_lpips.py
src/img_psnr.py
src/img_ssim.py
src/imgs2video.py
src/nc2raw.py
src/norm.py
src/tiff2vol.py
src/trim.py
src/vol_psnr.py
src/todo/iso_eval.py
src/todo/rotateVol.py
src/todo/volresize.py
src/utils/__init__.py
src/utils/filesUtils.py
src/utils/imgUtils.py
src/utils/metricUtils.py
src/utils/volumeUtils.py
pyscivistoolkit-0.0.5.dist-info/METADATA
pyscivistoolkit-0.0.5.dist-info/WHEEL
pyscivistoolkit-0.0.5.dist-info/entry_points.txt
pyscivistoolkit-0.0.5.dist-info/top_level.txt
pyscivistoolkit-0.0.5.dist-info/RECORD
