Metadata-Version: 2.4
Name: PySciVisToolKit
Version: 0.0.5
Summary: a simple toolkit for scivis
Author-email: Kaiyuan Tang <dullpigeon@gmail.com>
License: MIT
Classifier: Programming Language :: Python :: 3
Requires-Python: >=3.8.0
Requires-Dist: icecream>=2.1.3
Requires-Dist: imageio>=2.22.2
Requires-Dist: lpips>=0.1.4
Requires-Dist: netCDF4>=1.7.2
Requires-Dist: numpy>=1.23.3
Requires-Dist: opencv_python>=4.6.0.66
Requires-Dist: opencv_python_headless>=4.9.0.80
Requires-Dist: Pillow>=11.0.0
Requires-Dist: pytorch_msssim>=0.2.1
Requires-Dist: PyYAML>=6.0.2
Requires-Dist: scikit_image>=0.19.3
Requires-Dist: scikit_learn>=1.2.1
Requires-Dist: scipy>=1.10.0
Requires-Dist: tifffile>=2024.7.21
Requires-Dist: torch
Requires-Dist: torchvision
Requires-Dist: tqdm>=4.64.1
Requires-Dist: tyro>=0.9.2
Requires-Dist: Wand>=0.6.11
